jsondate3/__init__.py
jsondate3-0.1.3.dist-info/METADATA
jsondate3-0.1.3.dist-info/RECORD
jsondate3-0.1.3.dist-info/WHEEL
jsondate3-0.1.3.dist-info/top_level.txt
tests/__init__.py
tests/test_jsondate.py
