Metadata-Version: 2.1
Name: jsondate3
Version: 0.1.3
Summary: JSON with datetime support
Home-page: https://github.com/nitz14/jsondate
Author: Rick Harris, Maciej nitZ Krol
Author-email: rconradharris@gmail.com, nitz@o2.pl
License: MIT
Platform: any
Classifier: Environment :: Web Environment
Classifier: Intended Audience :: Developers
Classifier: License :: OSI Approved :: MIT License
Classifier: Operating System :: OS Independent
Classifier: Programming Language :: Python
Classifier: Topic :: Internet :: WWW/HTTP :: Dynamic Content
Classifier: Topic :: Software Development :: Libraries :: Python Modules
